globalsub.py
setup.py
globalsub.egg-info/PKG-INFO
globalsub.egg-info/SOURCES.txt
globalsub.egg-info/dependency_links.txt
globalsub.egg-info/not-zip-safe
globalsub.egg-info/top_level.txt