Metadata-Version: 1.0
Name: globalsub
Version: 1.0.2
Summary: Global substitution functions for Python unit tests
Home-page: http://pypi.python.org/pypi/globalsub/
Author: Mike Fletcher, Gustavo Niemeyer
Author-email: mcfletch@vrplumber.com
License: BSD
Platform: UNKNOWN
